{"cityName": "樟树", "days": 2, "cityImage": "", "spots": [{"title": "中国古海养生度假村", "address": "宜春市樟树市葛幺路中国古海养生旅游度假区", "image": "", "rank": 1, "time": 2, "location": {"lat": 27.995337551943873, "lng": 115.54726661963362}, "feature": {"sight_features": "特色1 养心、养性、养体", "sight_content": "中国古海养生旅游区，位于江西樟树，由易达旅游集团投资建设，占地6000亩，总投资31亿元，规划建设5大景区：古海养生旅游区、千年药都文化体验区、芳香植物养生旅游区、国际养生运动休闲区、世界养生文化体验区，打造国际一流的、复合型的养生旅游区。景区历时六年斥巨资打造，以盐药养生为核心，汇聚国内外中医、养生、道教等行业专家，与顶尖科研团队攻关研发，提取出樟树地下亿年养生盐卤精华，融合了樟树地道药材，结合道家经络学、养生学，独创一系列养生产品，帮助人们调节身体阴阳平衡，改善亚健康，延年益寿，为大众带来福音。中国古海以自然神奇资源、健康神奇疗效和神奇有趣玩法而闻名。首期拥有海洋之恋、玉盐炕、盐晶动感SPA、盐泥盐沙馆、海世界水上乐园等快乐盐养旅游项目；二期打造有“盐药养生”为核心，盐矿洞、盐砂洞、盐泥烘烤、盐药熏、盐药贴、盐乐冥想等为特色的盐界以及深睡馆等景点，开启“一漂盐海、二蒸盐洞、三躺盐炕、四埋盐沙、五抹盐泥、六吸盐雾、七贴盐药、八听盐乐”的全新旅游养生体验；三期将打造集观赏、娱乐互动、参与体验等为一体的古海白鹭景区，让游客在旅游中养生，在养生中旅游。\n\n\n海洋之恋——全国最大室内漂浮养生馆\n容纳千人的神奇死海，源自地下千米养生盐卤。脱离地心引力，全身放松，让温热死海水轻轻托着，尽享漂浮乐趣，旱鸭子和300斤大胖子也能自由漂。水中镁、锰等近200种矿物质微量元素加速新陈代谢，水润肌肤，美容瘦身效果佳。常漂古海，调节人体酸碱度略高于7，速效改善皮炎、风湿关节炎等45种以上身体症状。\n盐晶动感SPA——全球首家音乐养生SPA\n设有激流浴、涌泉浴等十几种世界流行的水疗类型，在梦幻“水吧”中享受世界级、全方位的中医穴位养生，每寸肌肤、每个穴位在不同强度水流冲击下得到按摩、放松。一冲一泡，轻松排出毒素。\n注：建议年长者不玩冲力大的水疗设备。最佳做SPA时间30分钟可以稍作休息，补充水份，再去玉盐炕休息。\n远古旷世盐疗——玉盐炕\n伴着樟木清香入眠，远古岩盐蒸气透过天然盐石加热深入肌肤，钠、氯离子渗透毛孔，促进血液循环，加上十分钟脚按，可达到身体最佳状态，获得健康疗养。\n盐沙盐泥馆——世界珍贵死海盐沙\n盐沙质地细腻，通过热盐掩埋和热敷，吸收亿万年的原生态盐沙天然矿物质精华。和家人朋友一起，将身体埋入盐沙中，发挥想象力摆出各种造型，在玩沙的同时还能体验盐泥美容之乐，深层洁净，美白肌肤。\n【盐界】\n盐矿洞——新型天然盐屋洞穴疗法\n风靡全球的盐屋洞穴，晶莹剔透的奇幻世界。古老盐矿石、 盐沙，在40度盐灯加温下释放出钠、氯离子，形成高浓度盐养空气，实现最为神奇的盐屋洞穴疗法。坐在原生态木条上，让盐养分子渗入肌肤，溶解脂肪、杀菌抗炎，让你瘦身同时远离亚健康。\n盐砂洞——全球罕见盐疗洞穴\n每一颗古海盐沙，都取自樟树地下千米亿年盐卤，同时融入道家养生秘制中草药。把自己全身深深埋入盐沙中，感受盐沙的温热，地下盐卤加温技术将盐药缓缓而充分释放，渗透身体每个细胞，去除体内湿气和毒素，对风湿关节炎、心血管疾病都有很好的疗效。\n盐泥烘烤——深层洁净 水润滋养\n古海盐泥，精粹亿万年深层死海盐泥能量，融汇大自然植物精华。盐泥蕴含强大矿物微量元素，源源不断地给肌肤补充养分，通过科学恒温的烘烤得到彻底释放，能深层清洁紧致肌肤，让肌肤排出毒素，重获水嫩光彩。\n盐药熏——盐药秘法熏蒸\n地上铺满珍贵百草，盐矿石上的熏炉散发浓郁的盐药香气，闭目养神，盘腿打坐，犹如置身仙境。盐药精华帮助舒经活络，畅通气血。适时饮用能量养生水，重启身体机能。\n盐乐冥想——五行盐乐冥想养生\n能治病的神奇音乐，听五行盐乐古曲，调理身体机能。静心盘坐在蒲团上，耳边回荡着五行盐乐，身下是亿万年温热盐卤，用音乐打开心情，用声音打开经络，达到曲终病好转的平衡养生。\n盐雾房——全国独创盐雾太极、瑜伽\n湿润盐雾扑面而来，像在海边练瑜伽。在盐雾房里舒展身体，在铺有盐卤地热的地面上做瑜珈、太极，盐雾中富含碘、溴、镁等微量元素，促进全身血液循环、身心得到化。\n盐油推拿——盐药秘方精油\n萃取樟树名贵草药、亿万年盐卤，经科学黄金配比提炼而成。静心享受专业技师的推拿按摩，让盐药精华迅速渗透肌肤，就能达到疏通经络、调和气血、缓解疲劳的功效。古海盐油推拿还配以盐泥全身双推，埃及艳后般的享受不虚此行。\n古海盐药贴——独家秘制专利产品\n古海独家秘制，将亿年深层养生盐卤融合陈年艾草，结合道家经络学、养生学精心研发而成，方便携带，随时享受古海特有的盐药养生，贴在身上暖暖的，通血活络、祛湿排毒、舒缓安神。每天一贴，身体更轻松\n深睡馆——漂浮30分钟等于熟睡4小时\n这里四墙隔音，静静躺在水面上，听着催眠曲，周身在古海卤溴、镁、钾等近200种矿物质及微量元素滋养和包裹、渗透之中，不知不觉进入梦乡，只要30分钟就能达到4小时的黄金睡眠，可改善失眠和体内阴阳、气血运行。\n海世界——全国最大的内陆海沙滩\n引进国际领先设备，设有海浪池水域区、沙滩、舞台、儿童池、烧烤区、酒吧、休息亭等，适合全家共同体验。动静皆宜的水上激情与快乐养生，领略不一样的海世界风情。\n\n\n精品酒店——海洋风精品养生酒店\n精品养生酒店共有山景别墅17栋、清泉别院3栋、桃花别院2栋。奢华的海洋风格，醉人的景观视界、迷你花园、近水楼台，浪漫高雅的海洋风环境，为您打造养眼、养身、养神、养心的私密休养空间。\n香泉宫——樟树最好的特色养生酒店\n由10幢风格简约、配套齐全的香泉别院组成。私家庭院豪华浪漫，宁静的环境，富于灵感的建筑格调和设计品位，配有死海漂浮池、无边界泳池，24小时管家式服务，带来独一无二入住体验。蓝调的特色养生酒店，足不出户尽享古海养生。\n美食养生餐厅——国家药膳美食基地\n国宝级美食养生大师以及国内顶级粤、湘、赣厨艺大师，以药膳为主体，集中医学、中药学、营养学、烹饪学之大成，将药文化与养生文化相结合形成的特色食疗，色、香、味、形、营养俱全，让您尽享舌尖上的养生。\n会务中心——航海会议\n包含多媒体会议室、贵宾会见厅、董事会议厅、多功能厅，20人-300人的大、中、小型会议室，配有豪华、前端设备。以“船”为主题，形似蔚蓝海域中航行的帆船，通透的视野环境，让会议变成一种享受。\n古海白鹭景区——白鹭主题综合性生态农庄\n以观鹭为核心，集观赏、娱乐互动、参与体验等为一体的综合性景点。项目包括观白鹭科普休闲游览、垂钓烧烤园、白鹭景区露营基地以及丰富、轻松、有趣、好玩的水上互动项目等，带给游客与众不同的观鹭体验和“游养”享受。\n引进国际领先设备，设有海浪池水域区、沙滩、舞台、儿童池、烧烤区、酒吧、休息亭等，适合全家共同体验。动静皆宜的水上激情与快乐养生，领略不一样的海世界风情。"}}, {"title": "阁皂山风景名胜区", "address": "宜春市樟树市601县道", "image": "", "rank": 2, "time": 3.5, "location": {"lat": 27.895428874401873, "lng": 115.59332776823598}, "feature": {"sight_features": "特色1 即有“天下名山，道教福地，神仙之馆”的誉称", "sight_content": "阁皂山风景区由阁皂山、玉华山、昭明山、梦湖度假区等景区组成，方圆二百余里，以其山川之秀、宫观之丽、古迹之异、峰岩之奇、传说之神成为闻名遐迩的旅游胜地。\n\n\n阁皂山不仅曾以道医著世，而且其山川风光，胜景天成，由骆驼、太极、玉女、凌云、丁仙诸峰环抱，中为腹地，诸峰高多为海拔500公尺左右，唯凌云峰海拔802.7公尺。天官赐福，天官名为上元一品赐福天官，紫微大帝，隶属玉清境。天官由青黄白三气结成，总主诸天帝王。每逢正月十五日，即下人间，校定人之罪福，故称天官赐福。\n著名道家葛玄在此悟道修真，在此山建“卧云庵”，筑坛立灶，-“九转金丹”，尊称樟树药业之祖。唐仪凤年间(676-678)朝廷赐阁皂山为天下第三十三福地。到宋代进入鼎盛时期，与金陵(今南京)茅山、广信(今贵溪)龙虎山并称为天下三大名山。"}}, {"title": "樟树市博物馆", "address": "宜春市樟树市鹿江南路", "image": "", "rank": 3, "time": 2.5, "location": {"lat": 28.056130653983566, "lng": 115.55070317180162}, "feature": {"sight_features": "", "sight_content": ""}}, {"title": "永镇塔", "address": "樟树市城南偏西17公里的永泰镇", "image": "", "rank": 4, "time": 2, "location": {"lat": 27.967307386970443, "lng": 115.47414573151899}, "feature": {"sight_features": "", "sight_content": ""}}, {"title": "吴城商代遗址", "address": "宜春市樟树市偏关县南楼沟乡吴城村", "image": "", "rank": 5, "time": 2, "location": {"lat": 27.99965696075474, "lng": 115.27679130692495}, "feature": {"sight_features": "", "sight_content": ""}}, {"title": "爱农湖景区", "address": "宜春市樟树市阁山镇爱农湖生态园木坑东南500米", "image": "", "rank": 6, "time": 2, "location": {"lat": 28.04867810320805, "lng": 115.64736858624019}, "feature": {"sight_features": "", "sight_content": ""}}, {"title": "药都公园", "address": "江西省宜春市樟树市楼门前", "image": "", "rank": 7, "time": 2, "location": {"lat": 28.06439359071412, "lng": 115.5523695985899}, "feature": {"sight_features": "", "sight_content": ""}}, {"title": "玉华山", "address": "西省樟树市、丰城市、和新干县交界处", "image": "", "rank": 8, "time": 2, "location": {"lat": 28.062153117647533, "lng": 115.55241893532511}, "feature": {"sight_features": "", "sight_content": ""}}, {"title": "樟树筑卫城遗址", "address": "江西省樟树市大桥街道办事处", "image": "", "rank": 9, "time": 1.5, "location": {"lat": 28.05748163578744, "lng": 115.59340717844304}, "feature": {"sight_features": "", "sight_content": ""}}, {"title": "开心岛水上乐园", "address": "曼哈顿向西500米维也纳售楼中心对面", "image": "", "rank": 10, "time": 2, "location": {"lat": 31.90472140528104, "lng": 121.17183482421433}, "feature": {"sight_features": "", "sight_content": ""}}, {"title": "高田葡萄专业合作社", "address": "324省道附近", "image": "", "rank": 11, "time": 2, "location": {"lat": 34.101022772229115, "lng": 117.56430801824291}, "feature": {"sight_features": "", "sight_content": ""}}, {"title": "庆仁药材种植基地(西南门)", "address": "228省道附近", "image": "", "rank": 12, "time": 2, "location": {"lat": 39.03858546081583, "lng": 117.03749267899916}, "feature": {"sight_features": "", "sight_content": ""}}, {"title": "啤酒广场", "address": "江西省宜春市樟树市沿江路药都广场附近(九龙湾附近)", "image": "", "rank": 13, "time": 2, "location": {"lat": 28.064327481697884, "lng": 115.5387330694274}, "feature": {"sight_features": "", "sight_content": ""}}, {"title": "吴城遗址", "address": "江西省樟树市吴城乡吴城村 331214", "image": "", "rank": 14, "time": 2, "location": {"lat": 27.99965696075474, "lng": 115.27679130692495}, "feature": {"sight_features": "", "sight_content": ""}}, {"title": "文昌宫", "address": "宜春市樟树市", "image": "", "rank": 15, "time": 0.4, "location": {"lat": 28.062153117647533, "lng": 115.55241893532511}, "feature": {"sight_features": "", "sight_content": ""}}, {"title": "草溪公园", "address": "杏佛路82号附近", "image": "", "rank": 16, "time": 2, "location": {"lat": 28.054875584842904, "lng": 115.54750746881534}, "feature": {"sight_features": "", "sight_content": ""}}, {"title": "瑶湖山庄", "address": "横洋段附近", "image": "", "rank": 17, "time": 2, "location": {"lat": 28.00320238073959, "lng": 115.51201315349964}, "feature": {"sight_features": "", "sight_content": ""}}, {"title": "福城公园", "address": "药都南大道61号4栋", "image": "", "rank": 18, "time": 2, "location": {"lat": 28.058320651244184, "lng": 115.54658533934523}, "feature": {"sight_features": "", "sight_content": ""}}, {"title": "阁山广场", "address": "樟店段附近", "image": "", "rank": 19, "time": 2, "location": {"lat": 27.96555699213014, "lng": 115.61345160826386}, "feature": {"sight_features": "", "sight_content": ""}}, {"title": "定安庙", "address": "843乡道附近", "image": "", "rank": 20, "time": 2, "location": {"lat": 39.87620087383098, "lng": 116.65036118218282}, "feature": {"sight_features": "", "sight_content": ""}}, {"title": "中国古海水世界", "address": "宜春市樟树市葛玄路中国古海养生旅游度假区", "image": "", "rank": 21, "time": 2, "location": {"lat": 27.995337551943873, "lng": 115.54726661963362}, "feature": {"sight_features": "", "sight_content": "中国古海水世界设有海浪池水域区、沙滩、草坪、舞台、儿童池、休息亭等，适合全家共同体验。\n海世界冲浪池可容纳3000人左右，乘着浪花跟随劲舞享受浪花的刺激，可以亲身投入海啸冲浪池中“赶大潮”，追潮、搏潮、逐潮、弄潮、戏潮，人工海浪让您尽享夏威夷风情。\n水世界引进国际先进造浪设备，0.3-1米人造海浪给游客带来不一样的冲浪体验，漂浮在海浪池中，可以观赏舞台上的不同表演；游玩于全国最大人工内陆海沙滩，犹如置身于大海；还有更多水上游玩设备双人皮艇、水上走球等，让游客尽情畅玩；动静皆宜的水上激情，领略不一样的海世界风情。儿童池内设有多种游玩设施，水上滑滑梯组合、七彩魔力圈等，让孩子们乐不思蜀。\n\n畅玩水上PARTY，酷热难耐的盛夏，不时顺“海”而上的浪花，更是冲溅起一身的愉悦和畅快，好不清爽！"}}, {"title": "罗马水汇", "address": "宜春市樟树市淦阳路8号财富春天1至3层", "image": "", "rank": 22, "time": 2.0, "location": {"lat": 28.06479932947938, "lng": 115.54709792953685}, "feature": {"sight_features": "", "sight_content": "江西樟树罗马水汇位于江西省宜春市樟树市淦阳路8号财富春天1至3层，是集洗浴、汗蒸、泡池、洗浴用品、儿童乐园、休息大厅于一体的休闲娱乐综合体。店内装修风格优雅舒适，是您友聚亲朋、商务休闲的理想场所。"}}, {"title": "余林彩春纪念科技馆", "address": "324省道", "image": "", "rank": 23, "time": 2, "location": {"lat": 34.101022772229115, "lng": 117.56430801824291}, "feature": {"sight_features": "", "sight_content": ""}}, {"title": "商务会展中心", "address": "药市路", "image": "", "rank": 24, "time": 2, "location": {"lat": 30.884491048007646, "lng": 103.59553246014526}, "feature": {"sight_features": "", "sight_content": ""}}, {"title": "樟树市图书馆", "address": "杏佛路63号", "image": "", "rank": 25, "time": 1.5, "location": {"lat": 28.055675433006723, "lng": 115.54752440906064}, "feature": {"sight_features": "", "sight_content": ""}}, {"title": "文艺展览馆", "address": "药都南大道", "image": "", "rank": 26, "time": 2, "location": {"lat": 28.053393261530214, "lng": 115.53635121775831}, "feature": {"sight_features": "", "sight_content": ""}}, {"title": "尚品画廊", "address": "府桥路", "image": "", "rank": 27, "time": 2, "location": {"lat": 28.05566320462587, "lng": 115.55513068160786}, "feature": {"sight_features": "", "sight_content": ""}}, {"title": "樟树美术馆", "address": "药都南大道70号", "image": "", "rank": 28, "time": 3.0, "location": {"lat": 28.0634101715354, "lng": 115.5538752367767}, "feature": {"sight_features": "", "sight_content": ""}}, {"title": "樟树市档案馆", "address": "药都路15号", "image": "", "rank": 29, "time": 1.0, "location": {"lat": 33.84634740841076, "lng": 115.77249167340413}, "feature": {"sight_features": "", "sight_content": ""}}, {"title": "三层楼兰三芽农家乐", "address": "阁山镇黄家巷三层楼村", "image": "", "rank": 30, "time": 2, "location": {"lat": 27.986874736923703, "lng": 115.59982167625701}, "feature": {"sight_features": "", "sight_content": ""}}, {"title": "三宝农家乐", "address": "三层楼", "image": "", "rank": 31, "time": 2, "location": {"lat": 26.738666404115886, "lng": 114.63754516416235}, "feature": {"sight_features": "", "sight_content": ""}}, {"title": "水晶宫歌剧院", "address": "市背街市背社区附近", "image": "", "rank": 32, "time": 2, "location": {"lat": 23.100931760317003, "lng": 113.27528273950196}, "feature": {"sight_features": "", "sight_content": ""}}, {"title": "樊城堆遗址", "address": "江西省樟树市刘公庙乡庙下村", "image": "", "rank": 33, "time": 2, "location": {"lat": 28.03950311966772, "lng": 115.33679562217387}, "feature": {"sight_features": "", "sight_content": ""}}, {"title": "经楼商业街", "address": "江西省樟树市张家山路附近", "image": "", "rank": 34, "time": 2, "location": {"lat": 28.08537230022075, "lng": 115.50024934878233}, "feature": {"sight_features": "", "sight_content": ""}}, {"title": "锦绣共和步行街", "address": "江西省樟树市共和西路", "image": "", "rank": 35, "time": 2, "location": {"lat": 28.068691991558712, "lng": 115.55140468462498}, "feature": {"sight_features": "", "sight_content": ""}}, {"title": "好玩吧儿童乐园", "address": "宜春市-樟树市-博彩超市1楼", "image": "", "rank": 36, "time": 2, "location": {"lat": 28.06775412084782, "lng": 115.57068185733709}, "feature": {"sight_features": "", "sight_content": ""}}, {"title": "中国古海", "address": "江西省宜春市樟树市南郊", "image": "", "rank": 37, "time": 2, "location": {"lat": 28.062153117647533, "lng": 115.55241893532511}, "feature": {"sight_features": "", "sight_content": ""}}]}